{"moduleDefinition":{"range":[1,1,1,30],"value":{"type":"normal","normal":{"moduleName":{"range":[1,8,1,16],"value":["HomePage"]},"exposingList":{"range":[1,17,1,30],"value":{"type":"all","all":[1,27,1,29]}}}}},"imports":[{"range":[3,1,3,26],"value":{"moduleName":{"range":[3,8,3,12],"value":["Html"]},"moduleAlias":null,"exposingList":{"range":[3,13,3,26],"value":{"type":"all","all":[3,23,3,25]}}}},{"range":[4,1,4,37],"value":{"moduleName":{"range":[4,8,4,23],"value":["Html","Attributes"]},"moduleAlias":null,"exposingList":{"range":[4,24,4,37],"value":{"type":"all","all":[4,34,4,36]}}}}],"declarations":[{"range":[6,1,10,4],"value":{"type":"function","function":{"documentation":null,"signature":null,"declaration":{"range":[6,1,10,4],"value":{"name":{"range":[6,1,6,5],"value":"main"},"arguments":[],"expression":{"range":[7,3,10,4],"value":{"type":"application","application":[{"range":[7,3,7,6],"value":{"type":"functionOrValue","functionOrValue":{"moduleName":[],"name":"div"}}},{"range":[7,7,7,25],"value":{"type":"list","list":[{"range":[7,9,7,24],"value":{"type":"application","application":[{"range":[7,9,7,14],"value":{"type":"functionOrValue","functionOrValue":{"moduleName":[],"name":"class"}}},{"range":[7,15,7,24],"value":{"type":"literal","literal":"wrapper"}}]}}]}},{"range":[7,25,10,4],"value":{"type":"list","list":[{"range":[8,5,8,54],"value":{"type":"application","application":[{"range":[8,5,8,8],"value":{"type":"functionOrValue","functionOrValue":{"moduleName":[],"name":"div"}}},{"range":[8,9,8,32],"value":{"type":"list","list":[{"range":[8,11,8,30],"value":{"type":"application","application":[{"range":[8,11,8,16],"value":{"type":"functionOrValue","functionOrValue":{"moduleName":[],"name":"style"}}},{"range":[8,17,8,24],"value":{"type":"literal","literal":"color"}},{"range":[8,25,8,30],"value":{"type":"literal","literal":"red"}}]}}]}},{"range":[8,32,8,54],"value":{"type":"list","list":[{"range":[8,34,8,53],"value":{"type":"application","application":[{"range":[8,34,8,38],"value":{"type":"functionOrValue","functionOrValue":{"moduleName":[],"name":"text"}}},{"range":[8,39,8,53],"value":{"type":"literal","literal":"Hello Wolrd!"}}]}}]}}]}},{"range":[9,5,9,27],"value":{"type":"application","application":[{"range":[9,5,9,9],"value":{"type":"functionOrValue","functionOrValue":{"moduleName":[],"name":"span"}}},{"range":[9,10,9,12],"value":{"type":"list","list":[]}},{"range":[9,12,9,27],"value":{"type":"list","list":[{"range":[9,14,9,25],"value":{"type":"application","application":[{"range":[9,14,9,18],"value":{"type":"functionOrValue","functionOrValue":{"moduleName":[],"name":"text"}}},{"range":[9,19,9,25],"value":{"type":"literal","literal":"Span"}}]}}]}}]}}]}}]}}}}}}}],"comments":[]}